Workbook

Sheet 📊 Dashboard
A1: 📊 QVAULT — Executive Dashboard
A2: Key metrics summary | All values linked from model sheets | Do not edit directly
A4: Total Supply | B4: Launch Price | C4: Initial FDV | D4: Fair Launch % | E4: Max APY | F4: Buyback Rate
A5: ='📋 Overview'!B5 -> 1000000000 | B5: ='📋 Overview'!B6 -> 0.001 | C5: ='📋 Overview'!B5*'📋 Overview'!B6 -> 1000000 | D5: =0.4 -> 0.4 | E5: =0.3 -> 0.3 | F5: ='📋 Overview'!B13 -> 0.4
A7: TOKEN DISTRIBUTION SUMMARY
A8: Allocation | B8: % Supply | C8: Tokens | D8: USD Value | E8: Vesting
A9: Fair Launch | B9: 0.4 | C9: ='📋 Overview'!C18 -> 400000000 | D9: ='📋 Overview'!D18 -> 400000 | E9: No lock
A10: Community | B10: 0.25 | C10: ='📋 Overview'!C19 -> 250000000 | D10: ='📋 Overview'!D19 -> 250000 | E10: 36m linear
A11: Treasury | B11: 0.15 | C11: ='📋 Overview'!C20 -> 150000000 | D11: ='📋 Overview'!D20 -> 150000 | E11: DAO vote
A12: Team | B12: 0.1 | C12: ='📋 Overview'!C21 -> 100000000 | D12: ='📋 Overview'!D21 -> 100000 | E12: 12m cliff + 24m
A13: Liquidity | B13: 0.07 | C13: ='📋 Overview'!C22 -> 70000000 | D13: ='📋 Overview'!D22 -> 70000 | E13: Protocol-locked
A14: Partners | B14: 0.03 | C14: ='📋 Overview'!C23 -> 30000000 | D14: ='📋 Overview'!D23 -> 30000 | E14: 6m cliff + 18m
A17: FEE SPLIT SUMMARY
A18: Destination | B18: % of Fees | C18: Purpose
A19: Staker Rewards | B19: 0.4 | C19: Weekly rewards to $QVLT stakers
A20: Buyback & Burn 🔥 | B20: 0.2 | C20: Open-market buyback → permanent burn
A21: DAO Treasury | B21: 0.25 | C21: Protocol development, grants, partnerships
A22: Growth & Marketing | B22: 0.15 | C22: Community growth, listings, campaigns

Sheet 📋 Overview
A1: ⬡ QVAULT ($QVLT) — Tokenomics Model
A2: Version 1.0 | May 2026 | All figures in USD unless noted | Blue = inputs, Black = formulas
A4: KEY PARAMETERS & ASSUMPTIONS
A5: Total Supply (tokens) | B5: 1000000000 | C5: Fixed supply — no additional minting
A6: Launch Price (USD) | B6: 0.001 | C6: Initial listing price assumption
A7: Initial Market Cap (USD) | B7: =B5*B6 -> 1000000 | C7: =B6*B7 -> 1000
A8: Target FDV at TGE (USD) | B8: 1000000 | C8: Fully diluted valuation at launch
A9: Assumed Peak Market Cap (Year 2) | B9: 50000000 | C9: Conservative bull case
A10: Annual Protocol Fee Revenue (Yr 1) | B10: 500000 | C10: Projected from staking + ecosystem
A11: Fee Growth Rate (YoY) | B11: 0.85 | C11: Year-over-year fee revenue growth
A12: Buyback Rate (% of fees) | B12: 0.2 | C12: % of fees used for buyback & burn
A13: Staker Reward Rate (% of fees) | B13: 0.4 | C13: % of fees distributed to stakers
A14: Expected Launch Date | B14: Q3 2026 | C14: Fair launch on Solana / Raydium
A16: TOKEN DISTRIBUTION
A17: Allocation | B17: % Supply | C17: Tokens | D17: USD Value @ Launch | E17: Vesting | F17: Unlock Schedule | G17: Color
A18: Fair Launch | B18: 0.4 | C18: =B18*$B$5 -> 400000000 | D18: =C18*$B$6 -> 400000 | E18: No lock — 100% at TGE | F18: 100% at TGE | G18: ●
A19: Community & Ecosystem | B19: 0.25 | C19: =B19*$B$5 -> 250000000 | D19: =C19*$B$6 -> 250000 | E19: 36-month linear vest | F19: ~2.78%/month | G19: ●
A20: DAO Treasury | B20: 0.15 | C20: =B20*$B$5 -> 150000000 | D20: =C20*$B$6 -> 150000 | E20: DAO governance controlled | F20: Per DAO vote | G20: ●
A21: Team & Advisors | B21: 0.1 | C21: =B21*$B$5 -> 100000000 | D21: =C21*$B$6 -> 100000 | E21: 12m cliff + 24m linear vest | F21: 0% → 8.3%/month | G21: ●
A22: Liquidity Provision | B22: 0.07 | C22: =B22*$B$5 -> 70000000 | D22: =C22*$B$6 -> 70000 | E22: Protocol-locked | F22: Locked in LP | G22: ●
A23: Strategic Partners | B23: 0.03 | C23: =B23*$B$5 -> 30000000 | D23: =C23*$B$6 -> 30000 | E23: 6m cliff + 18m linear vest | F23: 0% → 5.6%/month | G23: ●
A24: TOTAL | B24: =SUM(B18:B23) -> 1 | C24: =SUM(C18:C23) -> 1000000000 | D24: =SUM(D18:D23) -> 1000000

Sheet ⚡ Fee Mechanics
A1: ⚡ QVAULT — Fee Mechanics & Staking Model
A2: Fee distribution model | Staking tier yields | Linked to Overview assumptions
A4: PROTOCOL FEE DISTRIBUTION — ANNUAL PROJECTIONS
A5: Metric | B5: Year 1 | C5: Year 2 | D5: Year 3 | E5: Year 4 | F5: Year 5
A6: Gross Protocol Fees (USD) | B6: ='📋 Overview'!B11 -> 0.85 | C6: =B6*(1+'📋 Overview'!B12) -> 1.02 | D6: =C6*(1+'📋 Overview'!B12) -> 1.224 | E6: =D6*(1+'📋 Overview'!B12) -> 1.4688 | F6: =E6*(1+'📋 Overview'!B12) -> 1.76256
A7: → Staker Rewards (40%) | B7: ='📋 Overview'!B10 -> 500000 | C7: =B7*(1+'📋 Overview'!$B$11) -> 925000 | D7: =C7*(1+'📋 Overview'!$B$11) -> 1711250 | E7: =D7*(1+'📋 Overview'!$B$11) -> 3165812.5 | F7: =E7*(1+'📋 Overview'!$B$11) -> 5856753.1
A8: → Buyback & Burn (20%) | B8: =B7*'📋 Overview'!$B$13 -> 200000 | C8: =C7*'📋 Overview'!$B$13 -> 370000 | D8: =D7*'📋 Overview'!$B$13 -> 684500 | E8: =E7*'📋 Overview'!$B$13 -> 1266325 | F8: =F7*'📋 Overview'!$B$13 -> 2342701.2
A9: → DAO Treasury (25%) | B9: =B7*'📋 Overview'!$B$12 -> 100000 | C9: =C7*'📋 Overview'!$B$12 -> 185000 | D9: =D7*'📋 Overview'!$B$12 -> 342250 | E9: =E7*'📋 Overview'!$B$12 -> 633162.5 | F9: =F7*'📋 Overview'!$B$12 -> 1171350.6
A10: → Growth & Marketing (15%) | B10: =B7*0.25 -> 125000 | C10: =C7*0.25 -> 231250 | D10: =D7*0.25 -> 427812.5 | E10: =E7*0.25 -> 791453.12 | F10: =F7*0.25 -> 1464188.3
A11: Check (should = 100%) | B11: =B7*0.15 -> 75000 | C11: =C7*0.15 -> 138750 | D11: =D7*0.15 -> 256687.5 | E11: =E7*0.15 -> 474871.88 | F11: =F7*0.15 -> 878512.97
B12: =IF(B7=0,0,(B8+B9+B10+B11)/B7) -> 1 | C12: =IF(C7=0,0,(C8+C9+C10+C11)/C7) -> 1 | D12: =IF(D7=0,0,(D8+D9+D10+D11)/D7) -> 1 | E12: =IF(E7=0,0,(E8+E9+E10+E11)/E7) -> 1 | F12: =IF(F7=0,0,(F8+F9+F10+F11)/F7) -> 1
A14: STAKING TIERS — YIELD CALCULATOR
A15: Tier | B15: Min Stake (QVLT) | C15: Min Stake (USD) | D15: APY Low | E15: APY High | F15: Annual Yield Low | G15: Annual Yield High
A16: Electron ⚡ | B16: 10000 | C16: =B16*'📋 Overview'!$B$6 -> 10 | D16: 0.08 | E16: 0.12 | F16: =B16*D16*'📋 Overview'!$B$6 -> 0.8 | G16: =B16*E16*'📋 Overview'!$B$6 -> 1.2
A17: Photon 🔆 | B17: 50000 | C17: =B17*'📋 Overview'!$B$6 -> 50 | D17: 0.14 | E17: 0.2 | F17: =B17*D17*'📋 Overview'!$B$6 -> 7 | G17: =B17*E17*'📋 Overview'!$B$6 -> 10
A18: Qubit 🔐 | B18: 250000 | C18: =B18*'📋 Overview'!$B$6 -> 250 | D18: 0.22 | E18: 0.3 | F18: =B18*D18*'📋 Overview'!$B$6 -> 55 | G18: =B18*E18*'📋 Overview'!$B$6 -> 75
A21: HOLDER SCENARIO — BREAKEVEN & RETURN ANALYSIS
A22: Investment (USD) | B22: 1000
A23: Tokens Received | B23: =B22/'📋 Overview'!$B$6 -> 1000000
A24: Staking Tier | B24: Photon 🔆
A25: APY Assumed | B25: 0.17
A26: Annual Token Yield | B26: =B23*B25 -> 170000
A27: Annual USD Yield (@ launch price) | B27: =B26*'📋 Overview'!$B$6 -> 170
A28: Breakeven (months @ launch price) | B28: =IF(B27=0,"-",ROUND(12/(B27/B22),1)) -> 70.6
A29: 3x Return Price Target | B29: =3*'📋 Overview'!$B$6 -> 0.003
A30: 10x Return Price Target | B30: =10*'📋 Overview'!$B$6 -> 0.01

Sheet 📅 Vesting Schedule
A1: 📅 QVAULT — Token Vesting & Unlock Schedule
A2: Monthly token unlock by allocation (millions) | Columns = months from TGE
A4: Allocation / Month | B4: M1 | C4: M2 | D4: M3 | E4: M4 | F4: M5 | G4: M6 | H4: M7 | I4: M8 | J4: M9 | K4: M10 | L4: M11 | M4: M12 | N4: M13 | O4: M14 | P4: M15 | Q4: M16 | R4: M17 | S4: M18 | T4: M19 | U4: M20 | V4: M21 | W4: M22 | X4: M23 | Y4: M24 | Z4: M25 | AA4: M26 | AB4: M27 | AC4: M28 | AD4: M29 | AE4: M30 | AF4: M31 | AG4: M32 | AH4: M33 | AI4: M34 | AJ4: M35 | AK4: M36 | AL4: M37
A5: Fair Launch (400M) | B5: 400
A6: Community & Ecosystem (250M) | B6: 6.94 | C6: 6.94 | D6: 6.94 | E6: 6.94 | F6: 6.94 | G6: 6.94 | H6: 6.94 | I6: 6.94 | J6: 6.94 | K6: 6.94 | L6: 6.94 | M6: 6.94 | N6: 6.94 | O6: 6.94 | P6: 6.94 | Q6: 6.94 | R6: 6.94 | S6: 6.94 | T6: 6.94 | U6: 6.94 | V6: 6.94 | W6: 6.94 | X6: 6.94 | Y6: 6.94 | Z6: 6.94 | AA6: 6.94 | AB6: 6.94 | AC6: 6.94 | AD6: 6.94 | AE6: 6.94 | AF6: 6.94 | AG6: 6.94 | AH6: 6.94 | AI6: 6.94 | AJ6: 6.94 | AK6: 6.94
A7: DAO Treasury (150M) | G7: 5 | H7: 5 | I7: 5 | J7: 5 | K7: 5 | L7: 5 | M7: 5 | N7: 5 | O7: 5 | P7: 5 | Q7: 5 | R7: 5 | S7: 5 | T7: 5 | U7: 5 | V7: 5 | W7: 5 | X7: 5 | Y7: 5 | Z7: 5 | AA7: 5 | AB7: 5 | AC7: 5 | AD7: 5 | AE7: 5 | AF7: 5 | AG7: 5 | AH7: 5 | AI7: 5 | AJ7: 5
A8: Team & Advisors (100M) | N8: 4.17 | O8: 4.17 | P8: 4.17 | Q8: 4.17 | R8: 4.17 | S8: 4.17 | T8: 4.17 | U8: 4.17 | V8: 4.17 | W8: 4.17 | X8: 4.17 | Y8: 4.17 | Z8: 4.17 | AA8: 4.17 | AB8: 4.17 | AC8: 4.17 | AD8: 4.17 | AE8: 4.17 | AF8: 4.17 | AG8: 4.17 | AH8: 4.17 | AI8: 4.17 | AJ8: 4.17 | AK8: 4.17
A9: Liquidity (70M) | B9: 70
A10: Strategic Partners (30M) | H10: 1.67 | I10: 1.67 | J10: 1.67 | K10: 1.67 | L10: 1.67 | M10: 1.67 | N10: 1.67 | O10: 1.67 | P10: 1.67 | Q10: 1.67 | R10: 1.67 | S10: 1.67 | T10: 1.67 | U10: 1.67 | V10: 1.67 | W10: 1.67 | X10: 1.67 | Y10: 1.67
A11: TOTAL MONTHLY UNLOCK (M) | B11: =SUM(B5:B10) -> 476.94 | C11: =SUM(C5:C10) -> 6.94 | D11: =SUM(D5:D10) -> 6.94 | E11: =SUM(E5:E10) -> 6.94 | F11: =SUM(F5:F10) -> 6.94 | G11: =SUM(G5:G10) -> 11.94 | H11: =SUM(H5:H10) -> 13.61 | I11: =SUM(I5:I10) -> 13.61 | ... AL11: =SUM(AL5:AL10) -> 0
A12: CUMULATIVE CIRCULATING (M) | B12: =B11 -> 476.94 | C12: =B12+C11 -> 483.88 | D12: =C12+D11 -> 490.82 | E12: =D12+E11 -> 497.76 | F12: =E12+F11 -> 504.7 | G12: =F12+G11 -> 516.64 | H12: =G12+H11 -> 530.25 | I12: =H12+I11 -> 543.86 | J12: =I12+J11 -> 557.47 | ... AL12: =AK12+AL11 -> 999.98

Sheet 📈 Price Scenarios
A1: 📈 QVAULT — Price & Market Cap Scenario Analysis
A2: 3 scenarios × 5 years | Linked to Overview | Blue = inputs
A4: SCENARIO ASSUMPTIONS
A5: Assumption | B5: Bear 🐻 | D5: Base 📊 | F5: Bull 🚀
A6: Market Cap Year 1 (USD) | B6: 2000000 | D6: 10000000 | F6: 50000000
A7: Annual Growth Rate (Yrs 2-5) | B7: 0.2 | D7: 0.85 | F7: 2.5
A8: Peak Market Cap (USD) | B8: 5000000 | D8: 100000000 | F8: 500000000
A9: Price at Peak (USD) | B9: =B8/'📋 Overview'!$B$5 -> 0.005 | D9: =D8/'📋 Overview'!$B$5 -> 0.1 | F9: =F8/'📋 Overview'!$B$5 -> 0.5
A10: Return on $1,000 invested @ launch | B10: =1000*B9/'📋 Overview'!$B$6 -> 5000 | D10: =1000*D9/'📋 Overview'!$B$6 -> 100000 | F10: =1000*F9/'📋 Overview'!$B$6 -> 500000
A13: PRICE PROJECTION BY YEAR & SCENARIO
A14: Year | B14: Bear 🐻 — Market Cap | C14: Bear 🐻 — Price (USD) | D14: Base 📊 — Market Cap | E14: Base 📊 — Price (USD) | F14: Bull 🚀 — Market Cap | G14: Bull 🚀 — Price (USD)
A15: Year 1 | B15: =B6 -> 2000000 | C15: =B15/'📋 Overview'!$B$5 -> 0.002 | D15: =D6 -> 10000000 | E15: =D15/'📋 Overview'!$B$5 -> 0.01 | F15: =F6 -> 50000000 | G15: =F15/'📋 Overview'!$B$5 -> 0.05
A16: Year 2 | B16: =B15*(1+B7) -> 2400000 | C16: =B16/'📋 Overview'!$B$5 -> 0.0024 | D16: =D15*(1+D7) -> 18500000 | E16: =D16/'📋 Overview'!$B$5 -> 0.0185 | F16: =F15*(1+F7) -> 175000000 | G16: =F16/'📋 Overview'!$B$5 -> 0.175
A17: Year 3 | B17: =B16*(1+B7) -> 2880000 | C17: =B17/'📋 Overview'!$B$5 -> 0.00288 | D17: =D16*(1+D7) -> 34225000 | E17: =D17/'📋 Overview'!$B$5 -> 0.034225 | F17: =F16*(1+F7) -> 612500000 | G17: =F17/'📋 Overview'!$B$5 -> 0.6125
A18: Year 4 | B18: =B17*(1+B7) -> 3456000 | C18: =B18/'📋 Overview'!$B$5 -> 0.003456 | D18: =D17*(1+D7) -> 63316250 | E18: =D18/'📋 Overview'!$B$5 -> 0.06331625 | F18: =F17*(1+F7) -> 2143750000 | G18: =F18/'📋 Overview'!$B$5 -> 2.14375
A19: Year 5 | B19: =B18*(1+B7) -> 4147200 | C19: =B19/'📋 Overview'!$B$5 -> 0.0041472 | D19: =D18*(1+D7) -> 1.1713506e+08 | E19: =D19/'📋 Overview'!$B$5 -> 0.11713506 | F19: =F18*(1+F7) -> 7503125000 | G19: =F19/'📋 Overview'!$B$5 -> 7.503125
A22: ROI MATRIX — INVESTMENT SIZE × SCENARIO
A23: Investment (USD) | B23: Bear 🐻 — Peak Value | C23: Bear 🐻 — Return | D23: Base 📊 — Peak Value | E23: Base 📊 — Return | F23: Bull 🚀 — Peak Value | G23: Bull 🚀 — Return
A24: 100 | B24: =(A24/'📋 Overview'!$B$6)*(B8/'📋 Overview'!$B$5) -> 500 | C24: =B24-A24 -> 400 | D24: =(A24/'📋 Overview'!$B$6)*(D8/'📋 Overview'!$B$5) -> 10000 | E24: =D24-A24 -> 9900 | F24: =(A24/'📋 Overview'!$B$6)*(F8/'📋 Overview'!$B$5) -> 50000 | G24: =F24-A24 -> 49900
A25: 500 | B25: =(A25/'📋 Overview'!$B$6)*(B8/'📋 Overview'!$B$5) -> 2500 | C25: =B25-A25 -> 2000 | D25: =(A25/'📋 Overview'!$B$6)*(D8/'📋 Overview'!$B$5) -> 50000 | E25: =D25-A25 -> 49500 | F25: =(A25/'📋 Overview'!$B$6)*(F8/'📋 Overview'!$B$5) -> 250000 | G25: =F25-A25 -> 249500
A26: 1000 | B26: =(A26/'📋 Overview'!$B$6)*(B8/'📋 Overview'!$B$5) -> 5000 | C26: =B26-A26 -> 4000 | D26: =(A26/'📋 Overview'!$B$6)*(D8/'📋 Overview'!$B$5) -> 100000 | E26: =D26-A26 -> 99000 | F26: =(A26/'📋 Overview'!$B$6)*(F8/'📋 Overview'!$B$5) -> 500000 | G26: =F26-A26 -> 499000
A27: 5000 | B27: =(A27/'📋 Overview'!$B$6)*(B8/'📋 Overview'!$B$5) -> 25000 | C27: =B27-A27 -> 20000 | D27: =(A27/'📋 Overview'!$B$6)*(D8/'📋 Overview'!$B$5) -> 500000 | E27: =D27-A27 -> 495000 | F27: =(A27/'📋 Overview'!$B$6)*(F8/'📋 Overview'!$B$5) -> 2500000 | G27: =F27-A27 -> 2495000
A28: 10000 | B28: =(A28/'📋 Overview'!$B$6)*(B8/'📋 Overview'!$B$5) -> 50000 | C28: =B28-A28 -> 40000 | D28: =(A28/'📋 Overview'!$B$6)*(D8/'📋 Overview'!$B$5) -> 1000000 | E28: =D28-A28 -> 990000 | F28: =(A28/'📋 Overview'!$B$6)*(F8/'📋 Overview'!$B$5) -> 5000000 | G28: =F28-A28 -> 4990000
A29: 50000 | B29: =(A29/'📋 Overview'!$B$6)*(B8/'📋 Overview'!$B$5) -> 250000 | C29: =B29-A29 -> 200000 | D29: =(A29/'📋 Overview'!$B$6)*(D8/'📋 Overview'!$B$5) -> 5000000 | E29: =D29-A29 -> 4950000 | F29: =(A29/'📋 Overview'!$B$6)*(F8/'📋 Overview'!$B$5) -> 25000000 | G29: =F29-A29 -> 24950000

Sheet 🔥 Buyback & Burn
A1: 🔥 QVAULT — Buyback & Burn / Deflationary Model
A2: Models token supply reduction from buyback-and-burn | Deflationary pressure on $QVLT price
A4: ANNUAL BUYBACK & BURN PROJECTIONS
B5: Year 1 | C5: Year 2 | D5: Year 3 | E5: Year 4 | F5: Year 5 | G5: Notes
A6: Protocol Fees (USD) | B6: ='⚡ Fee Mechanics'!B7 -> 500000 | C6: ='⚡ Fee Mechanics'!C7 -> 925000 | D6: ='⚡ Fee Mechanics'!D7 -> 1711250 | E6: ='⚡ Fee Mechanics'!E7 -> 3165812.5 | F6: ='⚡ Fee Mechanics'!F7 -> 5856753.1 | G6: Linked from Fee Mechanics sheet
A7: Buyback Rate | B7: ='📋 Overview'!$B$12 -> 0.2 | C7: ='📋 Overview'!$B$12 -> 0.2 | D7: ='📋 Overview'!$B$12 -> 0.2 | E7: ='📋 Overview'!$B$12 -> 0.2 | F7: ='📋 Overview'!$B$12 -> 0.2 | G7: Linked from Overview assumptions
A8: USD Spent on Buyback | B8: =B6*B7 -> 100000 | C8: =C6*C7 -> 185000 | D8: =D6*D7 -> 342250 | E8: =E6*E7 -> 633162.5 | F8: =F6*F7 -> 1171350.6 | G8: Protocol USD used to buy $QVLT from market
A9: Avg Token Price (assumed) | B9: 0.001 | C9: 0.002 | D9: 0.005 | E9: 0.01 | F9: 0.02 | G9: Input: avg price assumption per year
A10: Tokens Bought & Burned | B10: =IF(B9=0,0,B8/B9) -> 100000000 | C10: =IF(C9=0,0,C8/C9) -> 92500000 | D10: =IF(D9=0,0,D8/D9) -> 68450000 | E10: =IF(E9=0,0,E8/E9) -> 63316250 | F10: =IF(F9=0,0,F8/F9) -> 58567531 | G10: USD spent ÷ avg price
A11: Cumulative Tokens Burned | B11: =B10 -> 100000000 | C11: =B11+C10 -> 192500000 | D11: =C11+D10 -> 260950000 | E11: =D11+E10 -> 324266250 | F11: =E11+F10 -> 3.8283378e+08 | G11: Running total burned since TGE
A12: Remaining Supply (B tokens) | B12: =('📋 Overview'!$B$5-B11)/1000000000 -> 0.9 | C12: =('📋 Overview'!$B$5-C11)/1000000000 -> 0.8075 | D12: =('📋 Overview'!$B$5-D11)/1000000000 -> 0.73905 | E12: =('📋 Overview'!$B$5-E11)/1000000000 -> 0.67573375 | F12: =('📋 Overview'!$B$5-F11)/1000000000 -> 0.61716622 | G12: 1B minus cumulative burned
A13: % Supply Burned | B13: =B11/'📋 Overview'!$B$5 -> 0.1 | C13: =C11/'📋 Overview'!$B$5 -> 0.1925 | D13: =D11/'📋 Overview'!$B$5 -> 0.26095 | E13: =E11/'📋 Overview'!$B$5 -> 0.32426625 | F13: =F11/'📋 Overview'!$B$5 -> 0.38283378 | G13: Deflationary % of original supply
